{
  "type": "FeatureCollection",
  "features": [
    {
      "type": "Feature",
      "properties": {
        "Name": null,
        "description": null,
        "timestamp": null,
        "begin": null,
        "end": null,
        "altitudeMode": null,
        "tessellate": -1,
        "extrude": 0,
        "visibility": -1,
        "drawOrder": null,
        "icon": null,
        "OBJECTID": 1,
        "Shape_Leng": 0.11635745319,
        "Shape_Area": 0.00078230679,
        "zone": "Newark Airport",
        "LocationID": 1,
        "borough": "EWR"
      },
      "geometry": {
        "type": "MultiPolygon",
        "coordinates": [
          [
            [
              [
                -74.184453,
                40.6949959999999
              ],
              [
                -74.184489,
                40.695095
              ],
              [
                -74.184498,
                40.695185
              ],
              [
                -74.184381,
                40.695878
              ],
              [
                -74.184021,
                40.6970749999999
              ],
              [
                -74.183913,
                40.697507
              ],
              [
                -74.183751,
                40.697795
              ],
              [
                -74.183634,
                40.698326
              ],
              [
                -74.1835619999999,
                40.6984519999999
              ],
              [
                -74.183544,
                40.69856
              ],
              [
                -74.183508,
                40.698704
              ],
              [
                -74.183274,
                40.70009
              ],
              [
                -74.1831569999999,
                40.7012149999999
              ],
              [
                -74.183166,
                40.702385
              ],
              [
                -74.183139,
                40.7026279999999
              ],
              [
                -74.183094,
                40.7028529999999
              ],
              [
                -74.182995,
                40.703159
              ],
              [
                -74.1828419999999,
                40.703465
              ],
              [
                -74.182644,
                40.703735
              ],
              [
                -74.182428,
                40.7039509999999
              ],
              [
                -74.182203,
                40.70414
              ],
              [
                -74.1820319999999,
                40.7042569999999
              ],
              [
                -74.181807,
                40.7043919999999
              ],
              [
                -74.181573,
                40.7045
              ],
              [
                -74.181321,
                40.704608
              ],
              [
                -74.180808,
                40.704788
              ],
              [
                -74.179467,
                40.7053459999999
              ],
              [
                -74.178873,
                40.7055439999999
              ],
              [
                -74.1783149999999,
                40.7057239999999
              ],
              [
                -74.177766,
                40.7058949999999
              ],
              [
                -74.177091,
                40.706093
              ],
              [
                -74.176992,
                40.706138
              ],
              [
                -74.176893,
                40.706192
              ],
              [
                -74.1766499999999,
                40.706417
              ],
              [
                -74.1764249999999,
                40.706696
              ],
              [
                -74.1762899999999,
                40.7068939999999
              ],
              [
                -74.176083,
                40.70711
              ],
              [
                -74.175993,
                40.707191
              ],
              [
                -74.175894,
                40.7072629999999
              ],
              [
                -74.1756599999999,
                40.70738
              ],
              [
                -74.175381,
                40.70747
              ],
              [
                -74.17476,
                40.707596
              ],
              [
                -74.174175,
                40.7076679999999
              ],
              [
                -74.173887,
                40.707731
              ],
              [
                -74.173473,
                40.707749
              ],
              [
                -74.172753,
                40.7078029999999
              ],
              [
                -74.171889,
                40.707911
              ],
              [
                -74.171637,
                40.707956
              ],
              [
                -74.17134,
                40.707965
              ],
              [
                -74.171205,
                40.707956
              ],
              [
                -74.169945,
                40.707974
              ],
              [
                -74.1688829999999,
                40.7079379999999
              ],
              [
                -74.166813,
                40.7078569999999
              ],
              [
                -74.164428,
                40.707794
              ],
              [
                -74.164014,
                40.707776
              ],
              [
                -74.16234,
                40.7077219999999
              ],
              [
                -74.160819,
                40.707641
              ],
              [
                -74.160333,
                40.707569
              ],
              [
                -74.160063,
                40.7074879999999
              ],
              [
                -74.159046,
                40.707146
              ],
              [
                -74.15892,
                40.70711
              ],
              [
                -74.158272,
                40.706876
              ],
              [
                -74.154591,
                40.705652
              ],
              [
                -74.154096,
                40.7054449999999
              ],
              [
                -74.154015,
                40.705382
              ],
              [
                -74.15388,
                40.705328
              ],
              [
                -74.153763,
                40.7054089999999
              ],
              [
                -74.153232,
                40.705247
              ],
              [
                -74.153178,
                40.705319
              ],
              [
                -74.15307,
                40.705283
              ],
              [
                -74.153592,
                40.704374
              ],
              [
                -74.153862,
                40.703843
              ],
              [
                -74.15514,
                40.701557
              ],
              [
                -74.155446,
                40.7010889999999
              ],
              [
                -74.1557519999999,
                40.7006659999999
              ],
              [
                -74.1560039999999,
                40.7002609999999
              ],
              [
                -74.156355,
                40.6997569999999
              ],
              [
                -74.157453,
                40.698092
              ],
              [
                -74.157543,
                40.6979389999999
              ],
              [
                -74.157588,
                40.6978129999999
              ],
              [
                -74.1576239999999,
                40.697678
              ],
              [
                -74.158299,
                40.6967059999999
              ],
              [
                -74.159514,
                40.6948879999999
              ],
              [
                -74.159586,
                40.6947619999999
              ],
              [
                -74.160144,
                40.694105
              ],
              [
                -74.160576,
                40.6932229999999
              ],
              [
                -74.162628,
                40.690289
              ],
              [
                -74.1627989999999,
                40.6900279999999
              ],
              [
                -74.162907,
                40.689875
              ],
              [
                -74.162952,
                40.689875
              ],
              [
                -74.163069,
                40.6898929999999
              ],
              [
                -74.1630959999999,
                40.689929
              ],
              [
                -74.163222,
                40.6899829999999
              ],
              [
                -74.163528,
                40.69001
              ],
              [
                -74.164104,
                40.6900819999999
              ],
              [
                -74.1641759999999,
                40.6900819999999
              ],
              [
                -74.16423,
                40.690055
              ],
              [
                -74.164365,
                40.6900369999999
              ],
              [
                -74.164509,
                40.6899829999999
              ],
              [
                -74.1646709999999,
                40.689884
              ],
              [
                -74.164797,
                40.6897579999999
              ],
              [
                -74.164914,
                40.6895869999999
              ],
              [
                -74.164995,
                40.6893889999999
              ],
              [
                -74.165283,
                40.688912
              ],
              [
                -74.165427,
                40.6887589999999
              ],
              [
                -74.165481,
                40.688633
              ],
              [
                -74.165607,
                40.688426
              ],
              [
                -74.165769,
                40.6880299999999
              ],
              [
                -74.165877,
                40.687877
              ],
              [
                -74.165823,
                40.6874899999999
              ],
              [
                -74.165805,
                40.687157
              ],
              [
                -74.165823,
                40.6870399999999
              ],
              [
                -74.165895,
                40.6868419999999
              ],
              [
                -74.166048,
                40.686554
              ],
              [
                -74.166399,
                40.6860229999999
              ],
              [
                -74.166507,
                40.6858879999999
              ],
              [
                -74.166741,
                40.6854919999999
              ],
              [
                -74.166957,
                40.685231
              ],
              [
                -74.167389,
                40.684547
              ],
              [
                -74.168046,
                40.683602
              ],
              [
                -74.1681629999999,
                40.6834759999999
              ],
              [
                -74.168226,
                40.6833499999999
              ],
              [
                -74.168487,
                40.682999
              ],
              [
                -74.168865,
                40.6823959999999
              ],
              [
                -74.169162,
                40.682
              ],
              [
                -74.169297,
                40.681784
              ],
              [
                -74.169477,
                40.681559
              ],
              [
                -74.169819,
                40.681019
              ],
              [
                -74.169954,
                40.680875
              ],
              [
                -74.1700529999999,
                40.6806679999999
              ],
              [
                -74.1704129999999,
                40.680155
              ],
              [
                -74.170512,
                40.6799929999999
              ],
              [
                -74.170674,
                40.679651
              ],
              [
                -74.170935,
                40.679291
              ],
              [
                -74.1714479999999,
                40.678472
              ],
              [
                -74.172006,
                40.677734
              ],
              [
                -74.172834,
                40.676564
              ],
              [
                -74.173149,
                40.676195
              ],
              [
                -74.17323,
                40.676078
              ],
              [
                -74.17359,
                40.675718
              ],
              [
                -74.174238,
                40.674935
              ],
              [
                -74.174373,
                40.674818
              ],
              [
                -74.175003,
                40.6741699999999
              ],
              [
                -74.176308,
                40.672766
              ],
              [
                -74.176416,
                40.6726219999999
              ],
              [
                -74.176632,
                40.6723969999999
              ],
              [
                -74.1767849999999,
                40.672181
              ],
              [
                -74.177091,
                40.671785
              ],
              [
                -74.177343,
                40.67156
              ],
              [
                -74.1775499999999,
                40.671425
              ],
              [
                -74.178027,
                40.6712089999999
              ],
              [
                -74.1786299999999,
                40.671038
              ],
              [
                -74.178882,
                40.671002
              ],
              [
                -74.179125,
                40.670993
              ],
              [
                -74.179332,
                40.671011
              ],
              [
                -74.179791,
                40.6711549999999
              ],
              [
                -74.17998,
                40.6712089999999
              ],
              [
                -74.180106,
                40.6712629999999
              ],
              [
                -74.180304,
                40.6712989999999
              ],
              [
                -74.181339,
                40.6717039999999
              ],
              [
                -74.18214,
                40.6720279999999
              ],
              [
                -74.1838499999999,
                40.672649
              ],
              [
                -74.1843719999999,
                40.67291
              ],
              [
                -74.184588,
                40.6730269999999
              ],
              [
                -74.185038,
                40.67336
              ],
              [
                -74.1851369999999,
                40.673459
              ],
              [
                -74.185479,
                40.673909
              ],
              [
                -74.1859469999999,
                40.6746649999999
              ],
              [
                -74.186703,
                40.67579
              ],
              [
                -74.187333,
                40.676744
              ],
              [
                -74.187675,
                40.6772929999999
              ],
              [
                -74.187954,
                40.6776169999999
              ],
              [
                -74.188197,
                40.677923
              ],
              [
                -74.188521,
                40.6784809999999
              ],
              [
                -74.188773,
                40.678859
              ],
              [
                -74.189052,
                40.679336
              ],
              [
                -74.189358,
                40.6797589999999
              ],
              [
                -74.189493,
                40.680092
              ],
              [
                -74.1897,
                40.6807939999999
              ],
              [
                -74.189781,
                40.681199
              ],
              [
                -74.189835,
                40.681316
              ],
              [
                -74.189916,
                40.681541
              ],
              [
                -74.18997,
                40.6818019999999
              ],
              [
                -74.189997,
                40.6822519999999
              ],
              [
                -74.189997,
                40.68263
              ],
              [
                -74.18997,
                40.682954
              ],
              [
                -74.189988,
                40.683179
              ],
              [
                -74.1899339999999,
                40.68371
              ],
              [
                -74.189871,
                40.6840789999999
              ],
              [
                -74.189781,
                40.684817
              ],
              [
                -74.189763,
                40.6850329999999
              ],
              [
                -74.189628,
                40.686104
              ],
              [
                -74.189556,
                40.6868959999999
              ],
              [
                -74.18952,
                40.687202
              ],
              [
                -74.189475,
                40.6874899999999
              ],
              [
                -74.1893939999999,
                40.687733
              ],
              [
                -74.1893939999999,
                40.687832
              ],
              [
                -74.189412,
                40.6879399999999
              ],
              [
                -74.189403,
                40.688093
              ],
              [
                -74.1893489999999,
                40.6882639999999
              ],
              [
                -74.189223,
                40.6886239999999
              ],
              [
                -74.188989,
                40.689047
              ],
              [
                -74.188701,
                40.6894429999999
              ],
              [
                -74.187792,
                40.69019
              ],
              [
                -74.187234,
                40.690595
              ],
              [
                -74.18637,
                40.691189
              ],
              [
                -74.185911,
                40.6914499999999
              ],
              [
                -74.1856319999999,
                40.691648
              ],
              [
                -74.184453,
                40.6949959999999
              ]
            ]
          ]
        ]
      }
    }
}